shelly/__init__.py
shelly/base_error_messag_sink.py
shelly/llm_parser.py
shelly/shelly.py
shelly/web_socket_error_message_sink.py
shelly_ai-0.1.4.dist-info/METADATA
shelly_ai-0.1.4.dist-info/WHEEL
shelly_ai-0.1.4.dist-info/entry_points.txt
shelly_ai-0.1.4.dist-info/licenses/LICENSE
shelly_ai-0.1.4.dist-info/RECORD
