Metadata-Version: 2.4
Name: shelly-ai
Version: 0.1.4
Summary: Kavia AI powered intelligent shell
Project-URL: Homepage, https://kavia.ai
Project-URL: Repository, https://github.com/Kavia-ai/shelly-ai
Author-email: Zoltan Kuscsik <zoltan@s57.io>
License: MIT
License-File: LICENSE
Requires-Python: >=3.9
Requires-Dist: aiohappyeyeballs==2.4.4
Requires-Dist: aiohttp==3.11.11
Requires-Dist: aiosignal==1.3.2
Requires-Dist: annotated-types==0.7.0
Requires-Dist: anyio==4.8.0
Requires-Dist: attrs==25.1.0
Requires-Dist: bidict==0.23.1
Requires-Dist: blinker==1.9.0
Requires-Dist: certifi==2025.1.31
Requires-Dist: charset-normalizer==3.4.1
Requires-Dist: click==8.1.8
Requires-Dist: distro==1.9.0
Requires-Dist: filelock==3.17.0
Requires-Dist: frozenlist==1.5.0
Requires-Dist: fsspec==2025.2.0
Requires-Dist: h11==0.14.0
Requires-Dist: httpcore==1.0.7
Requires-Dist: httpx==0.27.2
Requires-Dist: huggingface-hub==0.28.1
Requires-Dist: idna==3.10
Requires-Dist: importlib-metadata==8.6.1
Requires-Dist: itsdangerous==2.2.0
Requires-Dist: jinja2==3.1.5
Requires-Dist: jiter==0.8.2
Requires-Dist: jsonschema-specifications==2024.10.1
Requires-Dist: jsonschema==4.23.0
Requires-Dist: litellm==1.60.0
Requires-Dist: markupsafe==3.0.2
Requires-Dist: multidict==6.1.0
Requires-Dist: netifaces==0.10.6
Requires-Dist: openai==1.61.0
Requires-Dist: packaging==24.2
Requires-Dist: propcache==0.2.1
Requires-Dist: pydantic-core==2.27.2
Requires-Dist: pydantic==2.10.6
Requires-Dist: python-dotenv==1.0.1
Requires-Dist: python-engineio==4.11.2
Requires-Dist: python-socketio==5.12.1
Requires-Dist: pyyaml==6.0.2
Requires-Dist: referencing==0.36.2
Requires-Dist: regex==2024.11.6
Requires-Dist: requests==2.32.3
Requires-Dist: rpds-py==0.22.3
Requires-Dist: simple-websocket==1.1.0
Requires-Dist: sniffio==1.3.1
Requires-Dist: tiktoken==0.8.0
Requires-Dist: tokenizers==0.21.0
Requires-Dist: tqdm==4.67.1
Requires-Dist: typing-extensions==4.12.2
Requires-Dist: urllib3==2.3.0
Requires-Dist: websocket-client==1.8.0
Requires-Dist: wsproto==1.2.0
Requires-Dist: yarl==1.18.3
Requires-Dist: zipp==3.21.0
